zxgraphs/__init__.py
zxgraphs/py.typed
zxgraphs-0.0.post5.dist-info/LICENSE
zxgraphs-0.0.post5.dist-info/METADATA
zxgraphs-0.0.post5.dist-info/WHEEL
zxgraphs-0.0.post5.dist-info/top_level.txt
zxgraphs-0.0.post5.dist-info/RECORD
