Metadata-Version: 2.1
Name: zxgraphs
Version: 0.0.post5
Summary: A Python implementation of ZX graphs for quantum computing.
Home-page: https://github.com/hashberg-io/zxgraphs
Author: hashberg
Author-email: sg495@users.noreply.github.com
Project-URL: Bug Tracker, https://github.com/hashberg-io/zxgraphs/issues
Classifier: Development Status :: 1 - Planning
Classifier: Programming Language :: Python :: 3.11
Classifier: Programming Language :: Python :: 3.10
Classifier: Programming Language :: Python :: 3.9
Classifier: Operating System :: OS Independent
Classifier: Natural Language :: English
Classifier: Typing :: Typed
Requires-Python: >=3.9
License-File: LICENSE
Requires-Dist: typing-extensions
Provides-Extra: dev
Requires-Dist: mypy ; extra == 'dev'
Requires-Dist: pylint ; extra == 'dev'
Requires-Dist: pytest ; extra == 'dev'
Requires-Dist: pytest-cov ; extra == 'dev'
